rqalpha/__init__.py
rqalpha/__main__.py
rqalpha/_version.py
rqalpha/api.py
rqalpha/config.yml
rqalpha/const.py
rqalpha/environment.py
rqalpha/interface.py
rqalpha/main.py
rqalpha/mod_config.yml
rqalpha/user_module.py
rqalpha/apis/__init__.py
rqalpha/apis/api_abstract.py
rqalpha/apis/api_base.py
rqalpha/apis/api_rqdatac.py
rqalpha/apis/names.py
rqalpha/cmds/__init__.py
rqalpha/cmds/bundle.py
rqalpha/cmds/entry.py
rqalpha/cmds/misc.py
rqalpha/cmds/mod.py
rqalpha/cmds/run.py
rqalpha/cmds/test_run.py
rqalpha/core/__init__.py
rqalpha/core/events.py
rqalpha/core/execution_context.py
rqalpha/core/executor.py
rqalpha/core/global_var.py
rqalpha/core/strategy.py
rqalpha/core/strategy_context.py
rqalpha/core/strategy_loader.py
rqalpha/core/strategy_universe.py
rqalpha/data/__init__.py
rqalpha/data/bar_dict_price_board.py
rqalpha/data/bundle.py
rqalpha/data/data_proxy.py
rqalpha/data/trading_dates_mixin.py
rqalpha/data/base_data_source/__init__.py
rqalpha/data/base_data_source/adjust.py
rqalpha/data/base_data_source/data_source.py
rqalpha/data/base_data_source/storage_interface.py
rqalpha/data/base_data_source/storages.py
rqalpha/examples/IF1706_20161108.csv
rqalpha/examples/IF_macd.py
rqalpha/examples/buy_and_hold.py
rqalpha/examples/golden_cross.py
rqalpha/examples/macd.py
rqalpha/examples/pair_trading.py
rqalpha/examples/rsi.py
rqalpha/examples/run_code_demo.py
rqalpha/examples/run_file_demo.py
rqalpha/examples/run_func_demo.py
rqalpha/examples/subscribe_event.py
rqalpha/examples/test_pt.py
rqalpha/examples/turtle.py
rqalpha/examples/data_source/get_csv_module.py
rqalpha/examples/data_source/import_get_csv_module.py
rqalpha/examples/data_source/read_csv_as_df.py
rqalpha/examples/extend_api/rqalpha_mod_extend_api_demo.py
rqalpha/examples/extend_api/test_extend_api.py
rqalpha/mod/__init__.py
rqalpha/mod/utils.py
rqalpha/mod/rqalpha_mod_sys_accounts/__init__.py
rqalpha/mod/rqalpha_mod_sys_accounts/component_validator.py
rqalpha/mod/rqalpha_mod_sys_accounts/mod.py
beique-6.0.2.dist-info/LICENSE
beique-6.0.2.dist-info/METADATA
beique-6.0.2.dist-info/WHEEL
beique-6.0.2.dist-info/entry_points.txt
beique-6.0.2.dist-info/top_level.txt
beique-6.0.2.dist-info/RECORD
